{
  "UrlLocal": "spain_laliga/2014-2015/2015-05-02 - 19-00 Atl. Madrid 0 - 0 Ath Bilbao/",
  "UrlYoutube": "https://www.youtube.com/watch?v=ANjaOHM2TCk",
  "annotations": [
    {
      "id": 1,
      "start": "1 - 00:06:04.000",
      "end": "1 - 00:06:16.000"
    },
    {
      "id": 2,
      "start": "1 - 00:06:29.000",
      "end": "1 - 00:06:33.500"
    },
    {
      "id": 3,
      "start": "1 - 00:19:16.500",
      "end": "1 - 00:19:27.000"
    },
    {
      "id": 4,
      "start": "1 - 00:19:34.000",
      "end": "1 - 00:19:40.000"
    },
    {
      "id": 5,
      "start": "1 - 00:39:50.000",
      "end": "1 - 00:39:57.500"
    },
    {
      "id": 6,
      "start": "1 - 00:40:54.000",
      "end": "1 - 00:40:58.500"
    },
    {
      "id": 7,
      "start": "1 - 00:41:30.000",
      "end": "1 - 00:41:46.500"
    },
    {
      "id": 8,
      "start": "1 - 00:42:20.500",
      "end": "1 - 00:42:25.000"
    },
    {
      "id": 9,
      "start": "1 - 00:42:27.000",
      "end": "1 - 00:42:44.000"
    },
    {
      "id": 10,
      "start": "1 - 00:42:56.000",
      "end": "1 - 00:43:08.500"
    },
    {
      "id": 11,
      "start": "2 - 00:07:30.000",
      "end": "2 - 00:07:46.500"
    },
    {
      "id": 12,
      "start": "2 - 00:07:53.500",
      "end": "2 - 00:08:14.500"
    },
    {
      "id": 13,
      "start": "2 - 00:10:29.000",
      "end": "2 - 00:10:46.500"
    },
    {
      "id": 14,
      "start": "2 - 00:10:59.000",
      "end": "2 - 00:11:06.000"
    },
    {
      "id": 15,
      "start": "2 - 00:12:22.500",
      "end": "2 - 00:12:37.500"
    },
    {
      "id": 16,
      "start": "2 - 00:13:19.500",
      "end": "2 - 00:13:27.000"
    },
    {
      "id": 17,
      "start": "2 - 00:14:19.500",
      "end": "2 - 00:14:29.000"
    },
    {
      "id": 18,
      "start": "2 - 00:21:27.000",
      "end": "2 - 00:21:31.500"
    },
    {
      "id": 19,
      "start": "2 - 00:26:06.500",
      "end": "2 - 00:26:25.000"
    },
    {
      "id": 20,
      "start": "2 - 00:26:29.500",
      "end": "2 - 00:26:39.500"
    },
    {
      "id": 21,
      "start": "2 - 00:28:47.000",
      "end": "2 - 00:29:03.000"
    },
    {
      "id": 22,
      "start": "2 - 00:33:24.500",
      "end": "2 - 00:33:34.000"
    },
    {
      "id": 23,
      "start": "2 - 00:42:52.500",
      "end": "2 - 00:43:04.500"
    },
    {
      "id": 24,
      "start": "2 - 00:47:26.000",
      "end": "2 - 00:47:36.500"
    },
    {
      "id": 25,
      "start": "2 - 00:47:48.500",
      "end": "2 - 00:47:52.500"
    },
    {
      "id": 26,
      "start": "2 - 00:48:10.500",
      "end": "2 - 00:48:31.500"
    },
    {
      "id": 27,
      "start": "2 - 00:48:49.500",
      "end": "2 - 00:48:54.000"
    },
    {
      "id": 28,
      "start": "2 - 00:48:57.000",
      "end": "2 - 00:49:00.500"
    },
    {
      "id": 29,
      "start": "2 - 00:49:33.500",
      "end": "2 - 00:49:47.000"
    }
  ],
  "gameAwayTeam": "Ath Bilbao",
  "gameDate": "02/05/2015 - 19:00",
  "gameHomeTeam": "Atl. Madrid",
  "gameScore": "0 - 0",
  "summaryLength": "05:17"
}